{
  "AltLookAngle": {
    "x": 0,
    "y": 0,
    "z": 0
  },
  "Autoraise": true,
  "ColorDiffuse": {
    "a": 0.5098,
    "b": 1,
    "g": 1,
    "r": 1
  },
  "Description": "",
  "DragSelectable": true,
  "GMNotes": "",
  "GUID": "ec5625",
  "Grid": true,
  "GridProjection": false,
  "Hands": false,
  "HideWhenFaceDown": false,
  "IgnoreFoW": false,
  "LayoutGroupSortIndex": 0,
  "Locked": true,
  "LuaScript": "",
  "LuaScriptState": "",
  "MeasureMovement": false,
  "Name": "ScriptingTrigger",
  "Nickname": "Zone Player Skill Slot Green R3",
  "Snap": true,
  "Sticky": true,
  "Tags": [
    "area_green",
    "skill_token_combat",
    "skill_token_mage",
    "skill_token_rogue",
    "skill_token_warrior"
  ],
  "Tooltip": true,
  "Transform": {
    "posX": 57.384,
    "posY": 0.95,
    "posZ": -28.705,
    "rotX": 0,
    "rotY": 0,
    "rotZ": 0,
    "scaleX": 0.59,
    "scaleY": 0.5,
    "scaleZ": 0.61
  },
  "Value": 0,
  "XmlUI": ""
}
